Metadata-Version: 2.1
Name: swagger-spec-compatibility
Version: 1.3.4
Summary: Python library to check Swagger Spec backward compatibility
Home-page: https://github.com/Yelp/swagger-spec-compatibility
Author: Yelp, Inc.
Author-email: opensource+swagger-spec-compatibility@yelp.com
License: Copyright Yelp, Inc. 2018
Platform: UNKNOWN
Classifier: Development Status :: 5 - Production/Stable
Classifier: Environment :: Console
Classifier: Intended Audience :: Developers
Classifier: Topic :: Software Development :: Libraries :: Python Modules
Classifier: License :: OSI Approved :: MIT License
Classifier: Operating System :: OS Independent
Classifier: Programming Language :: Python :: 2
Classifier: Programming Language :: Python :: 2.7
Classifier: Programming Language :: Python :: 3
Classifier: Programming Language :: Python :: 3.5
Classifier: Programming Language :: Python :: 3.6
Classifier: Programming Language :: Python :: 3.7
Requires-Dist: bravado
Requires-Dist: bravado-core (!=5.16.0)
Requires-Dist: swagger-spec-validator
Requires-Dist: six
Requires-Dist: termcolor
Requires-Dist: typing-extensions
Requires-Dist: venusian
Requires-Dist: functools32 ; python_version<"3.2"
Requires-Dist: typing ; python_version<"3.5"
